HACKING.md
MANIFEST.in
README.md
config.py.example
setup.py
bugzfeed/__init__.py
bugzfeed/cache.py
bugzfeed/pulse.py
bugzfeed/server.py
bugzfeed/simple_server.py
bugzfeed/subscriptions.py
bugzfeed/websocket.py
bugzfeed.egg-info/PKG-INFO
bugzfeed.egg-info/SOURCES.txt
bugzfeed.egg-info/dependency_links.txt
bugzfeed.egg-info/entry_points.txt
bugzfeed.egg-info/requires.txt
bugzfeed.egg-info/top_level.txt
example/example.js
example/index.html
example/jquery-1.10.2.min.js