Metadata-Version: 1.1
Name: bugzfeed
Version: 0.3
Summary: notification system for Bugzilla via WebSockets
Home-page: http://github.com/mozilla/bugzfeed/
Author: Mark Cote
Author-email: mcote@mozilla.com
License: Mozilla Public License 2.0
Platform: any
Classifier: Development Status :: 4 - Beta
Classifier: Environment :: Web Environment
Classifier: Intended Audience :: Developers
Classifier: License :: OSI Approved :: Mozilla Public License 2.0 (MPL 2.0)
Classifier: Operating System :: OS Independent
Classifier: Programming Language :: Python
Classifier: Topic :: Internet :: WWW/HTTP
